tipsql/version.py
tipsql-0.0.14.dist-info/METADATA
tipsql-0.0.14.dist-info/WHEEL
tipsql-0.0.14.dist-info/RECORD
