Metadata-Version: 2.1
Name: tipsql
Version: 0.0.14
Summary: Type Hint SQL Query Builder for Python.
Author: yassun7010
Author-email: yassun7010@outlook.com
Requires-Python: >=3.12,<4.0
Classifier: Programming Language :: Python :: 3
Classifier: Programming Language :: Python :: 3.12
Provides-Extra: cli
Provides-Extra: postgresql
Provides-Extra: snowflake
Provides-Extra: sqlite3
Requires-Dist: inflection (>=0.5.1,<0.6.0) ; extra == "cli"
Requires-Dist: jinja2 (>=3.1.2,<4.0.0) ; extra == "cli"
Requires-Dist: tipsql-cli (==0.0.14) ; extra == "cli"
Requires-Dist: tipsql-core (==0.0.14)
Requires-Dist: tipsql-postgresql (==0.0.14) ; extra == "postgresql"
Requires-Dist: tipsql-snowflake (==0.0.14) ; extra == "snowflake"
Requires-Dist: tipsql-sqlite3 (==0.0.14) ; extra == "sqlite3"
